elementy/__init__.py
elementy/_version.py
elementy/element.py
elementy/elements.py
elementy/periodictable.py
elementy/py.typed
elementy-0.0.18.dist-info/LICENSE
elementy-0.0.18.dist-info/METADATA
elementy-0.0.18.dist-info/WHEEL
elementy-0.0.18.dist-info/top_level.txt
elementy-0.0.18.dist-info/RECORD
